setup.py
notch/__init__.py
notch.client.egg-info/PKG-INFO
notch.client.egg-info/SOURCES.txt
notch.client.egg-info/dependency_links.txt
notch.client.egg-info/namespace_packages.txt
notch.client.egg-info/not-zip-safe
notch.client.egg-info/requires.txt
notch.client.egg-info/top_level.txt
notch/client/__init__.py
notch/client/client.py
notch/client/errors.py
notch/client/lb_transport.py
notch/client/shard.py