Metadata-Version: 1.0
Name: notch.client
Version: 0.5
Summary: The Notch Client Library
Home-page: http://bitbucket.org/enemesco/notch-client
Author: Andrew Fort
Author-email: andrew.fort+pypi@gmail.com
License: http://www.apache.org/licenses/LICENSE-2.0
Platform: UNKNOWN
Classifier: Development Status :: 2 - Pre-Alpha
Classifier: Environment :: Console
Classifier: Intended Audience :: System Administrators
Classifier: License :: OSI Approved :: Apache Software License
Classifier: Operating System :: POSIX
Classifier: Programming Language :: Python :: 2.6
Classifier: Topic :: System :: Networking :: Monitoring
Classifier: Topic :: System :: Systems Administration
